forloop_common_structures/__init__.py
forloop_common_structures/database_models.py
forloop_common_structures/core/__init__.py
forloop_common_structures/core/browser_elements.py
forloop_common_structures/core/database.py
forloop_common_structures/core/dataset.py
forloop_common_structures/core/dbtable.py
forloop_common_structures/core/edge.py
forloop_common_structures/core/file.py
forloop_common_structures/core/initial_variable.py
forloop_common_structures/core/job.py
forloop_common_structures/core/node.py
forloop_common_structures/core/pipeline.py
forloop_common_structures/core/plan.py
forloop_common_structures/core/popup.py
forloop_common_structures/core/project.py
forloop_common_structures/core/result.py
forloop_common_structures/core/script.py
forloop_common_structures/core/session.py
forloop_common_structures/core/trigger.py
forloop_common_structures/core/user.py
forloop_common_structures/core/user_flow_step.py
forloop_common_structures/core/user_resource.py
forloop_common_structures/core/variable.py
forloop_common_structures-0.5.6.dist-info/LICENSE
forloop_common_structures-0.5.6.dist-info/METADATA
forloop_common_structures-0.5.6.dist-info/WHEEL
forloop_common_structures-0.5.6.dist-info/top_level.txt
forloop_common_structures-0.5.6.dist-info/RECORD
