Metadata-Version: 2.1
Name: forloop_common_structures
Version: 0.5.6
Summary: This package contains open source core structures and schemas within Forloop.ai execution core and API
Home-page: https://github.com/ForloopAI/forloop_common_structures
Author: DovaX
Author-email: dovax.ai@gmail.com
Classifier: Programming Language :: Python :: 3
Classifier: License :: OSI Approved :: MIT License
Classifier: Operating System :: OS Independent
Requires-Python: >=3.6
License-File: LICENSE
